lazyregistry/__init__.py
lazyregistry/_version.py
lazyregistry/pretrained.py
lazyregistry/py.typed
lazyregistry/registry.py
lazyregistry-0.3.4.dist-info/METADATA
lazyregistry-0.3.4.dist-info/WHEEL
lazyregistry-0.3.4.dist-info/licenses/LICENSE
lazyregistry-0.3.4.dist-info/RECORD
