Metadata-Version: 2.4
Name: lazyregistry
Version: 0.3.4
Summary: A lightweight Python library for lazy-loading registries with namespace support and type safety.
Project-URL: Homepage, https://github.com/milkclouds/lazyregistry
Project-URL: Repository, https://github.com/milkclouds/lazyregistry
Project-URL: Issues, https://github.com/milkclouds/lazyregistry/issues
Project-URL: Changelog, https://github.com/milkclouds/lazyregistry/releases
Author-email: Suhwan Choi <milkclouds00@gmail.com>
License: MIT
License-File: LICENSE
Keywords: lazy-loading,namespace,plugin,pretrained,registry,type-safe
Classifier: Development Status :: 4 - Beta
Classifier: Intended Audience :: Developers
Classifier: License :: OSI Approved :: MIT License
Classifier: Programming Language :: Python :: 3
Classifier: Programming Language :: Python :: 3.9
Classifier: Programming Language :: Python :: 3.10
Classifier: Programming Language :: Python :: 3.11
Classifier: Programming Language :: Python :: 3.12
Classifier: Programming Language :: Python :: 3.13
Classifier: Topic :: Software Development :: Libraries :: Python Modules
Classifier: Typing :: Typed
Requires-Python: >=3.9
Requires-Dist: pydantic>=2.0
